LICENSE
README.md
setup.py
mkdocs_te/__init__.py
mkdocs_te/data_cleaning.py
mkdocs_te/doc_generation.py
mkdocs_te/main.py
mkdocs_te/usable.py
mkdocs_te.egg-info/PKG-INFO
mkdocs_te.egg-info/SOURCES.txt
mkdocs_te.egg-info/dependency_links.txt
mkdocs_te.egg-info/top_level.txt