Metadata-Version: 2.1
Name: mkdocs-te
Version: 0.0.1
Summary: UNKNOWN
Home-page: https://github.com/fga-eps-mds/2022-2-Squad07
Author: Bruno Martins, Rafael Nobre, Diógenes Júnior, Bruno Ribeiro, Igor Penha
Author-email: diogjunior10071@gmail.com
License: MIT License
Keywords: Pacote
Platform: UNKNOWN
License-File: LICENSE
